{"version": 0.6, "generator": "Overpass API 0.7.62.1 084b4234", "osm3s": {"timestamp_osm_base": "2024-05-16T18:26:51Z", "copyright": "The data included in this document is from www.openstreetmap.org. The data is made available under ODbL."}, "elements": [{"type": "node", "id": 2277143151, "lat": 56.1167172, "lon": 47.4467464, "tags": {"bus": "yes", "highway": "bus_stop", "name": "\u041c\u0430\u0433\u0430\u0437\u0438\u043d \"\u041d\u0438\u043a\u0430\"", "name:cv": "\"\u041d\u0438\u043a\u0430\" \u043b\u0430\u0432\u043a\u043a\u0430", "public_transport": "platform", "shelter": "yes", "trolleybus": "yes"}}, {"type": "node", "id": 2277143155, "lat": 56.1161917, "lon": 47.4476235, "tags": {"bus": "yes", "highway": "bus_stop", "name": "\u041c\u0430\u0433\u0430\u0437\u0438\u043d \"\u041d\u0438\u043a\u0430\"", "name:cv": "\"\u041d\u0438\u043a\u0430\" \u043b\u0430\u0432\u043a\u043a\u0430", "public_transport": "platform", "shelter": "yes"}}]}