{"version": 0.6, "generator": "Overpass API 0.7.62.1 084b4234", "osm3s": {"timestamp_osm_base": "2024-05-14T01:05:35Z", "copyright": "The data included in this document is from www.openstreetmap.org. The data is made available under ODbL."}, "elements": [{"type": "node", "id": 6138684759, "lat": 52.7573842, "lon": 103.6367921}, {"type": "node", "id": 6138684760, "lat": 52.7565897, "lon": 103.6379557}, {"type": "node", "id": 6138684761, "lat": 52.7566883, "lon": 103.6381404}, {"type": "node", "id": 6138684762, "lat": 52.7574689, "lon": 103.6369541}, {"type": "node", "id": 7894703680, "lat": 52.757145, "lon": 103.63925}, {"type": "node", "id": 7894703681, "lat": 52.7573655, "lon": 103.639659}, {"type": "node", "id": 7894703682, "lat": 52.7572931, "lon": 103.6397655}, {"type": "node", "id": 7894703683, "lat": 52.7570727, "lon": 103.6393565}, {"type": "way", "id": 655156207, "nodes": [6138684759, 6138684760, 6138684761, 6138684762, 6138684759], "tags": {"access": "yes", "amenity": "parking", "fee": "no", "parking": "surface", "supervised": "no", "surface": "asphalt"}}, {"type": "way", "id": 846188518, "nodes": [7894703680, 7894703681, 7894703682, 7894703683, 7894703680], "tags": {"amenity": "parking"}}]}