{"version": 0.6, "generator": "Overpass API 0.7.62.1 084b4234", "osm3s": {"timestamp_osm_base": "2024-05-17T12:01:40Z", "copyright": "The data included in this document is from www.openstreetmap.org. The data is made available under ODbL."}, "elements": [{"type": "node", "id": 8058428268, "lat": 59.9872099, "lon": 30.2115534, "tags": {"amenity": "clinic", "name": "\u041c\u0435\u0442\u043e\u0434\u0438\u043a\u0430", "opening_hours": "Mo-Fr 09:00-21:00; Sa,Su 09:00-20:00", "phone": "+78123300507", "website": "https://metodikaspb.ru/"}}]}