{"version": 0.6, "generator": "Overpass API 0.7.62.1 084b4234", "osm3s": {"timestamp_osm_base": "2024-05-14T10:47:15Z", "copyright": "The data included in this document is from www.openstreetmap.org. The data is made available under ODbL."}, "elements": [{"type": "node", "id": 5161932267, "lat": 55.6070728, "lon": 37.2861823}, {"type": "node", "id": 5161932268, "lat": 55.6061296, "lon": 37.2878071}, {"type": "node", "id": 5161932269, "lat": 55.6060755, "lon": 37.2877116}, {"type": "node", "id": 5161932270, "lat": 55.6070178, "lon": 37.2860827}, {"type": "node", "id": 11172244905, "lat": 55.6060866, "lon": 37.2877311}, {"type": "way", "id": 531827128, "nodes": [5161932270, 5161932269, 11172244905, 5161932268, 5161932267, 5161932270], "tags": {"bench": "yes", "layer": "-2", "location": "underground", "network": "\u0410\u044d\u0440\u043e\u044d\u043a\u0441\u043f\u0440\u0435\u0441\u0441", "public_transport": "platform", "railway": "platform", "tunnel": "yes"}}]}