{"version": 0.6, "generator": "Overpass API 0.7.62.1 084b4234", "osm3s": {"timestamp_osm_base": "2024-05-17T04:43:51Z", "copyright": "The data included in this document is from www.openstreetmap.org. The data is made available under ODbL."}, "elements": [{"type": "node", "id": 418735327, "lat": 55.7513055, "lon": 37.596234}, {"type": "node", "id": 418735329, "lat": 55.7511765, "lon": 37.5963153}, {"type": "node", "id": 418735340, "lat": 55.7510373, "lon": 37.5955833}, {"type": "node", "id": 418735342, "lat": 55.7509316, "lon": 37.5957209}, {"type": "node", "id": 418735434, "lat": 55.7502856, "lon": 37.5992591}, {"type": "node", "id": 418735435, "lat": 55.7502673, "lon": 37.5996331}, {"type": "node", "id": 418735436, "lat": 55.7501767, "lon": 37.5996215}, {"type": "node", "id": 418735437, "lat": 55.7501919, "lon": 37.5992471}, {"type": "node", "id": 669249041, "lat": 55.7502855, "lon": 37.5995833}, {"type": "node", "id": 669249042, "lat": 55.7502694, "lon": 37.5995813}, {"type": "node", "id": 669249043, "lat": 55.7502751, "lon": 37.5995184}, {"type": "node", "id": 669249044, "lat": 55.7502881, "lon": 37.5995201}, {"type": "way", "id": 35814540, "nodes": [418735327, 418735329, 418735342, 418735340, 418735327], "tags": {"addr:housenumber": "12 \u04411", "addr:street": "\u0443\u043b\u0438\u0446\u0430 \u0410\u0440\u0431\u0430\u0442", "building": "commercial", "building:architecture": "art_nouveau", "building:colour": "orange;brown;white", "building:levels": "3", "building:material": "plaster", "roof:angle": "30", "roof:colour": "maroon", "roof:material": "metal", "roof:shape": "hipped"}}, {"type": "way", "id": 35814554, "nodes": [418735434, 669249043, 669249044, 669249041, 669249042, 418735435, 418735436, 418735437, 418735434], "tags": {"addr:housenumber": "31\u0410", "addr:street": "\u0413\u043e\u0433\u043e\u043b\u0435\u0432\u0441\u043a\u0438\u0439 \u0431\u0443\u043b\u044c\u0432\u0430\u0440", "building": "commercial", "building:levels": "3", "country": "AZ", "diplomatic": "embassy", "embassy": "residence", "name": "\u0420\u0435\u0437\u0438\u0434\u0435\u043d\u0446\u0438\u044f \u043f\u043e\u0441\u043b\u0430 \u0410\u0437\u0435\u0440\u0431\u0430\u0439\u0434\u0436\u0430\u043d\u0430", "name:ru": "\u0420\u0435\u0437\u0438\u0434\u0435\u043d\u0446\u0438\u044f \u043f\u043e\u0441\u043b\u0430 \u0410\u0437\u0435\u0440\u0431\u0430\u0439\u0434\u0436\u0430\u043d\u0430", "office": "diplomatic", "target": "RU"}}]}