{"version": 0.6, "generator": "Overpass API 0.7.62.1 084b4234", "osm3s": {"timestamp_osm_base": "2024-05-18T00:21:25Z", "copyright": "The data included in this document is from www.openstreetmap.org. The data is made available under ODbL."}, "elements": [{"type": "node", "id": 548693595, "lat": 51.6533383, "lon": 39.1883811}, {"type": "node", "id": 548693598, "lat": 51.6528312, "lon": 39.1889384}, {"type": "node", "id": 548693606, "lat": 51.6527694, "lon": 39.1887923}, {"type": "node", "id": 548693612, "lat": 51.6532765, "lon": 39.188235}, {"type": "node", "id": 779528318, "lat": 51.6567588, "lon": 39.1886235, "tags": {"entrance": "staircase", "ref": "3"}}, {"type": "node", "id": 779528324, "lat": 51.6565747, "lon": 39.1880625}, {"type": "node", "id": 779528326, "lat": 51.6569932, "lon": 39.1883192, "tags": {"entrance": "yes", "ref": "1"}}, {"type": "node", "id": 779528329, "lat": 51.6565386, "lon": 39.1881055, "tags": {"entrance": "yes", "ref": "5"}}, {"type": "node", "id": 779528331, "lat": 51.6569493, "lon": 39.188221}, {"type": "node", "id": 779528334, "lat": 51.6571638, "lon": 39.1883265}, {"type": "node", "id": 779528336, "lat": 51.6570498, "lon": 39.1881013}, {"type": "node", "id": 779528338, "lat": 51.6567179, "lon": 39.1888963}, {"type": "node", "id": 779528342, "lat": 51.6565075, "lon": 39.1879153}, {"type": "node", "id": 779601815, "lat": 51.6541575, "lon": 39.1897487}, {"type": "node", "id": 779601818, "lat": 51.6537596, "lon": 39.1904442}, {"type": "node", "id": 779601820, "lat": 51.6536897, "lon": 39.1902861}, {"type": "node", "id": 779601823, "lat": 51.6542274, "lon": 39.1899068}, {"type": "node", "id": 779604305, "lat": 51.6534213, "lon": 39.1912105}, {"type": "node", "id": 779604308, "lat": 51.6536375, "lon": 39.1906162}, {"type": "node", "id": 779604311, "lat": 51.6536705, "lon": 39.1906875}, {"type": "node", "id": 779604315, "lat": 51.6532948, "lon": 39.1911388}, {"type": "node", "id": 779604318, "lat": 51.6538125, "lon": 39.1908327}, {"type": "node", "id": 779604320, "lat": 51.6532636, "lon": 39.1910713}, {"type": "node", "id": 779604327, "lat": 51.6532148, "lon": 39.1911299}, {"type": "node", "id": 779604330, "lat": 51.6536856, "lon": 39.1905584}, {"type": "node", "id": 779604333, "lat": 51.6534361, "lon": 39.1916085}, {"type": "node", "id": 779604336, "lat": 51.6535449, "lon": 39.1914778}, {"type": "node", "id": 779616849, "lat": 51.6530218, "lon": 39.1909909}, {"type": "node", "id": 779616852, "lat": 51.653023, "lon": 39.1912235}, {"type": "node", "id": 779616853, "lat": 51.6532667, "lon": 39.1918032}, {"type": "node", "id": 779616856, "lat": 51.6531656, "lon": 39.1919136}, {"type": "node", "id": 779616857, "lat": 51.6528545, "lon": 39.1911736}, {"type": "node", "id": 779616859, "lat": 51.6530891, "lon": 39.1911512}, {"type": "node", "id": 779621877, "lat": 51.6535715, "lon": 39.1928501}, {"type": "node", "id": 779621879, "lat": 51.6536693, "lon": 39.1927442}, {"type": "node", "id": 779621881, "lat": 51.6532851, "lon": 39.192163}, {"type": "node", "id": 779621883, "lat": 51.6533829, "lon": 39.1920571}, {"type": "node", "id": 781748356, "lat": 51.6528909, "lon": 39.1891323}, {"type": "node", "id": 781748358, "lat": 51.6531268, "lon": 39.1896876}, {"type": "node", "id": 781748359, "lat": 51.6532691, "lon": 39.1895305}, {"type": "node", "id": 781748360, "lat": 51.6533079, "lon": 39.1896216}, {"type": "node", "id": 781748363, "lat": 51.6538144, "lon": 39.1890623}, {"type": "node", "id": 781748369, "lat": 51.6537453, "lon": 39.1888996}, {"type": "node", "id": 781748375, "lat": 51.6531965, "lon": 39.1895057}, {"type": "node", "id": 781748377, "lat": 51.6529909, "lon": 39.1890218}, {"type": "node", "id": 781755697, "lat": 51.6536231, "lon": 39.1885046}, {"type": "node", "id": 781755700, "lat": 51.6537206, "lon": 39.1883967}, {"type": "node", "id": 781755702, "lat": 51.6539032, "lon": 39.1888256}, {"type": "node", "id": 781755704, "lat": 51.6537744, "lon": 39.188968}, {"type": "node", "id": 781755706, "lat": 51.6537765, "lon": 39.188865}, {"type": "node", "id": 781766558, "lat": 51.6533187, "lon": 39.1896097, "tags": {"amenity": "post_box", "fixme": "\u0423\u0442\u043e\u0447\u043d\u0438\u0442\u044c \u043d\u043e\u043c\u0435\u0440 \u0438 \u0432\u0440\u0435\u043c\u044f \u0432\u044b\u0435\u043c\u043a\u0438 \u043f\u0438\u0441\u0435\u043c", "operator": "\u0424\u0413\u0423\u041f \"\u041f\u043e\u0447\u0442\u0430 \u0420\u043e\u0441\u0441\u0438\u0438\"", "post_box:type": "wall", "source": "local_knowledge", "source:position": "bing", "website": "https://russianpost.ru/"}}, {"type": "node", "id": 824423082, "lat": 51.6532303, "lon": 39.1895733}, {"type": "node", "id": 824795907, "lat": 51.6548529, "lon": 39.1854462}, {"type": "node", "id": 824795909, "lat": 51.6545537, "lon": 39.186868}, {"type": "node", "id": 824795910, "lat": 51.6552092, "lon": 39.1862911}, {"type": "node", "id": 824795911, "lat": 51.6548828, "lon": 39.1851845}, {"type": "node", "id": 824795912, "lat": 51.6548491, "lon": 39.1867119}, {"type": "node", "id": 824795913, "lat": 51.6546796, "lon": 39.1856386}, {"type": "node", "id": 824795914, "lat": 51.6546134, "lon": 39.1854835}, {"type": "node", "id": 824795916, "lat": 51.6548865, "lon": 39.1869129}, {"type": "node", "id": 824795917, "lat": 51.6545632, "lon": 39.1866685}, {"type": "node", "id": 824795918, "lat": 51.6553791, "lon": 39.1863417}, {"type": "node", "id": 826105756, "lat": 51.6539789, "lon": 39.1874256}, {"type": "node", "id": 826105757, "lat": 51.6526116, "lon": 39.1884608}, {"type": "node", "id": 826105759, "lat": 51.6540854, "lon": 39.1874522}, {"type": "node", "id": 826105763, "lat": 51.6535902, "lon": 39.1873915}, {"type": "node", "id": 826105765, "lat": 51.6535196, "lon": 39.1872237}, {"type": "node", "id": 826105769, "lat": 51.6536613, "lon": 39.1872683}, {"type": "node", "id": 826105772, "lat": 51.6536472, "lon": 39.1870881}, {"type": "node", "id": 826105775, "lat": 51.6525411, "lon": 39.188293}, {"type": "node", "id": 826105777, "lat": 51.6535751, "lon": 39.1873556}, {"type": "node", "id": 826105779, "lat": 51.6541082, "lon": 39.187215}, {"type": "node", "id": 826105781, "lat": 51.6539843, "lon": 39.1873539}, {"type": "node", "id": 826107749, "lat": 51.6531098, "lon": 39.1868634}, {"type": "node", "id": 826107751, "lat": 51.6524514, "lon": 39.1879113}, {"type": "node", "id": 826107753, "lat": 51.6521952, "lon": 39.1869146}, {"type": "node", "id": 826107754, "lat": 51.6529993, "lon": 39.1871751}, {"type": "node", "id": 826107755, "lat": 51.652448, "lon": 39.1877108}, {"type": "node", "id": 826107757, "lat": 51.6529981, "lon": 39.1871025}, {"type": "node", "id": 826107759, "lat": 51.6522109, "lon": 39.1878186}, {"type": "node", "id": 826107761, "lat": 51.6523146, "lon": 39.187739}, {"type": "node", "id": 826107763, "lat": 51.6531141, "lon": 39.1871701}, {"type": "node", "id": 826107765, "lat": 51.6523036, "lon": 39.187079}, {"type": "node", "id": 1013224464, "lat": 51.6532388, "lon": 39.189459}, {"type": "node", "id": 1382796037, "lat": 51.6561505, "lon": 39.1875513}, {"type": "node", "id": 1382796041, "lat": 51.6562144, "lon": 39.187429}, {"type": "node", "id": 1382796043, "lat": 51.6562293, "lon": 39.1874642}, {"type": "node", "id": 1382796044, "lat": 51.6562732, "lon": 39.1878397}, {"type": "node", "id": 1382796045, "lat": 51.6563011, "lon": 39.1876041, "tags": {"entrance": "yes", "ref": "1"}}, {"type": "node", "id": 1382796046, "lat": 51.6563755, "lon": 39.1877266}, {"type": "node", "id": 1382796047, "lat": 51.6564847, "lon": 39.1871302}, {"type": "node", "id": 1382796056, "lat": 51.6565, "lon": 39.1871662}, {"type": "node", "id": 1382796058, "lat": 51.656534, "lon": 39.1873467, "tags": {"entrance": "yes", "ref": "2"}}, {"type": "node", "id": 1382796060, "lat": 51.6565639, "lon": 39.1870955}, {"type": "node", "id": 1382796062, "lat": 51.6565949, "lon": 39.1874898}, {"type": "node", "id": 1382796063, "lat": 51.6566879, "lon": 39.187387}, {"type": "node", "id": 1806100855, "lat": 51.6532194, "lon": 39.1894804}, {"type": "node", "id": 1806100856, "lat": 51.6532497, "lon": 39.1895519}, {"type": "node", "id": 1845106383, "lat": 51.6540622, "lon": 39.1904267}, {"type": "node", "id": 1845106384, "lat": 51.6540813, "lon": 39.1905258}, {"type": "node", "id": 1845106386, "lat": 51.6540858, "lon": 39.1903334}, {"type": "node", "id": 1845106388, "lat": 51.654097, "lon": 39.1905086}, {"type": "node", "id": 1845106390, "lat": 51.6541166, "lon": 39.1906052}, {"type": "node", "id": 1845106392, "lat": 51.6541318, "lon": 39.1905903}, {"type": "node", "id": 1845106394, "lat": 51.6541629, "lon": 39.1906634}, {"type": "node", "id": 1845106396, "lat": 51.6541968, "lon": 39.1902141}, {"type": "node", "id": 1845106398, "lat": 51.6542284, "lon": 39.1906644}, {"type": "node", "id": 1845106408, "lat": 51.6542696, "lon": 39.1902193}, {"type": "node", "id": 1845106409, "lat": 51.6542958, "lon": 39.1902886}, {"type": "node", "id": 1845106410, "lat": 51.6543091, "lon": 39.1902742}, {"type": "node", "id": 1845106411, "lat": 51.6543268, "lon": 39.190371}, {"type": "node", "id": 1845106412, "lat": 51.6543299, "lon": 39.1905428}, {"type": "node", "id": 1845106413, "lat": 51.6543407, "lon": 39.1903577}, {"type": "node", "id": 1845106414, "lat": 51.6543512, "lon": 39.1904355}, {"type": "node", "id": 1988051813, "lat": 51.6521827, "lon": 39.1870371}, {"type": "node", "id": 1988051815, "lat": 51.6521842, "lon": 39.187123}, {"type": "node", "id": 1988051817, "lat": 51.6521879, "lon": 39.1872831}, {"type": "node", "id": 1988051819, "lat": 51.6521909, "lon": 39.1874665}, {"type": "node", "id": 1988051820, "lat": 51.6521942, "lon": 39.1876201}, {"type": "node", "id": 1988051821, "lat": 51.6521972, "lon": 39.1870365}, {"type": "node", "id": 1988051822, "lat": 51.6521975, "lon": 39.1878192}, {"type": "node", "id": 1988051823, "lat": 51.6522091, "lon": 39.1871219}, {"type": "node", "id": 1988051824, "lat": 51.65221, "lon": 39.1874657}, {"type": "node", "id": 1988051825, "lat": 51.6522117, "lon": 39.187282}, {"type": "node", "id": 1988051826, "lat": 51.6522125, "lon": 39.1876193}, {"type": "node", "id": 1988051827, "lat": 51.6522126, "lon": 39.1879217}, {"type": "node", "id": 1988051836, "lat": 51.6522493, "lon": 39.1868836}, {"type": "node", "id": 1988051839, "lat": 51.6522498, "lon": 39.1869122}, {"type": "node", "id": 1988051841, "lat": 51.6523046, "lon": 39.1871376}, {"type": "node", "id": 1988051843, "lat": 51.6523073, "lon": 39.1872945}, {"type": "node", "id": 1988051846, "lat": 51.6523096, "lon": 39.1874281}, {"type": "node", "id": 1988051848, "lat": 51.6523122, "lon": 39.1875918}, {"type": "node", "id": 1988051850, "lat": 51.6523167, "lon": 39.1871371}, {"type": "node", "id": 1988051852, "lat": 51.6523193, "lon": 39.187294}, {"type": "node", "id": 1988051854, "lat": 51.6523239, "lon": 39.1874275}, {"type": "node", "id": 1988051856, "lat": 51.6523267, "lon": 39.1875911}, {"type": "node", "id": 1988051857, "lat": 51.6523663, "lon": 39.1877144}, {"type": "node", "id": 1988051858, "lat": 51.6523667, "lon": 39.1877368}, {"type": "node", "id": 1988051859, "lat": 51.6523702, "lon": 39.1868784}, {"type": "node", "id": 1988051860, "lat": 51.6523708, "lon": 39.1869145}, {"type": "node", "id": 1988051861, "lat": 51.6523859, "lon": 39.1870754}, {"type": "node", "id": 1988051862, "lat": 51.6523861, "lon": 39.1870913}, {"type": "node", "id": 1988051863, "lat": 51.6524939, "lon": 39.186875}, {"type": "node", "id": 1988051864, "lat": 51.6524945, "lon": 39.1869091}, {"type": "node", "id": 1988051865, "lat": 51.6525053, "lon": 39.1870682}, {"type": "node", "id": 1988051866, "lat": 51.6525056, "lon": 39.1870862}, {"type": "node", "id": 1988051879, "lat": 51.6526049, "lon": 39.1870639}, {"type": "node", "id": 1988051881, "lat": 51.6526052, "lon": 39.1870824}, {"type": "node", "id": 1988051883, "lat": 51.6526096, "lon": 39.18687}, {"type": "node", "id": 1988051886, "lat": 51.6526102, "lon": 39.1869045}, {"type": "node", "id": 1988051888, "lat": 51.6527189, "lon": 39.1868656}, {"type": "node", "id": 1988051890, "lat": 51.6527195, "lon": 39.1868998}, {"type": "node", "id": 1988051892, "lat": 51.6527362, "lon": 39.1870559}, {"type": "node", "id": 1988051894, "lat": 51.6527366, "lon": 39.1870767}, {"type": "node", "id": 1988051895, "lat": 51.652824, "lon": 39.1870521}, {"type": "node", "id": 1988051896, "lat": 51.6528243, "lon": 39.1870682}, {"type": "node", "id": 1988051897, "lat": 51.6528393, "lon": 39.1868604}, {"type": "node", "id": 1988051898, "lat": 51.6528399, "lon": 39.1868969}, {"type": "node", "id": 1988051899, "lat": 51.6529143, "lon": 39.1870417}, {"type": "node", "id": 1988051900, "lat": 51.6529147, "lon": 39.1870643}, {"type": "node", "id": 1988051901, "lat": 51.6529386, "lon": 39.1868547}, {"type": "node", "id": 1988051902, "lat": 51.6529392, "lon": 39.1868926}, {"type": "node", "id": 1988051903, "lat": 51.6530094, "lon": 39.1870375}, {"type": "node", "id": 1988051904, "lat": 51.6530105, "lon": 39.187102}, {"type": "node", "id": 1988051906, "lat": 51.6530573, "lon": 39.1868496}, {"type": "node", "id": 1988051919, "lat": 51.6530575, "lon": 39.1868657}, {"type": "node", "id": 1988051921, "lat": 51.6531118, "lon": 39.1869825}, {"type": "node", "id": 1988051924, "lat": 51.6531126, "lon": 39.1870834}, {"type": "node", "id": 1988051926, "lat": 51.6531259, "lon": 39.1869819}, {"type": "node", "id": 1988051928, "lat": 51.6531276, "lon": 39.1870828}, {"type": "node", "id": 2974330508, "lat": 51.6542453, "lon": 39.1918215}, {"type": "node", "id": 2974330509, "lat": 51.6543262, "lon": 39.1919939}, {"type": "node", "id": 3096869874, "lat": 51.6534755, "lon": 39.1911454}, {"type": "node", "id": 3096869875, "lat": 51.653503, "lon": 39.1912049}, {"type": "node", "id": 3096869876, "lat": 51.6537087, "lon": 39.1909579}, {"type": "node", "id": 3096869877, "lat": 51.6536803, "lon": 39.1908963}, {"type": "node", "id": 3096875818, "lat": 51.6537325, "lon": 39.1908336}, {"type": "node", "id": 3096875819, "lat": 51.6537608, "lon": 39.1908948}, {"type": "node", "id": 3116421906, "lat": 51.6550976, "lon": 39.191054}, {"type": "node", "id": 3116421907, "lat": 51.6550168, "lon": 39.1908817}, {"type": "node", "id": 3116421908, "lat": 51.6537454, "lon": 39.1924305}, {"type": "node", "id": 3116421909, "lat": 51.6538263, "lon": 39.1926028}, {"type": "node", "id": 3656468734, "lat": 51.6567864, "lon": 39.1885879}, {"type": "node", "id": 3656468735, "lat": 51.6569626, "lon": 39.188359}, {"type": "node", "id": 3656468736, "lat": 51.6569499, "lon": 39.1883329}, {"type": "node", "id": 3656468737, "lat": 51.6567708, "lon": 39.1885516}, {"type": "node", "id": 3656468738, "lat": 51.6563685, "lon": 39.1880717}, {"type": "node", "id": 3656468739, "lat": 51.6564881, "lon": 39.18794}, {"type": "node", "id": 3656468741, "lat": 51.6563253, "lon": 39.1876609}, {"type": "node", "id": 3656468742, "lat": 51.6563404, "lon": 39.1876442}, {"type": "node", "id": 3828004561, "lat": 51.6529219, "lon": 39.1913339}, {"type": "node", "id": 3828004562, "lat": 51.6530938, "lon": 39.1913921}, {"type": "node", "id": 3828004563, "lat": 51.6529928, "lon": 39.1915025}, {"type": "node", "id": 4139506095, "lat": 51.653286, "lon": 39.1895702, "tags": {"entrance": "yes", "source": "local_knowledge", "source:position": "bing"}}, {"type": "node", "id": 4543068416, "lat": 51.6568502, "lon": 39.1884546, "tags": {"entrance": "yes", "ref": "2"}}, {"type": "node", "id": 4543072720, "lat": 51.6566491, "lon": 39.1883653, "tags": {"entrance": "yes", "ref": "4"}}, {"type": "node", "id": 5153679736, "lat": 51.6551355, "lon": 39.1861163}, {"type": "node", "id": 5153679737, "lat": 51.6552367, "lon": 39.1860097}, {"type": "way", "id": 43474279, "nodes": [548693595, 548693598, 548693606, 548693612, 548693595], "tags": {"addr:city": "\u0412\u043e\u0440\u043e\u043d\u0435\u0436", "addr:housenumber": "107", "addr:postcode": "394006", "addr:street": "\u0443\u043b\u0438\u0446\u0430 20-\u043b\u0435\u0442\u0438\u044f \u041e\u043a\u0442\u044f\u0431\u0440\u044f", "building": "apartments", "building:levels": "5"}}, {"type": "way", "id": 62424218, "nodes": [779528342, 3656468739, 3656468738, 779528338, 779528334, 779528336, 779528331, 779528326, 3656468735, 3656468736, 4543068416, 3656468737, 3656468734, 779528318, 4543072720, 779528329, 779528324, 779528342], "tags": {"addr:city": "\u0412\u043e\u0440\u043e\u043d\u0435\u0436", "addr:housenumber": "26", "addr:postcode": "394006", "addr:street": "\u0443\u043b\u0438\u0446\u0430 \u041a\u0438\u0440\u043e\u0432\u0430", "building": "apartments", "building:levels": "5"}}, {"type": "way", "id": 62436542, "nodes": [779601815, 779601823, 779601818, 779601820, 779601815], "tags": {"addr:city": "\u0412\u043e\u0440\u043e\u043d\u0435\u0436", "addr:housenumber": "88", "addr:postcode": "394006", "addr:street": "\u0443\u043b\u0438\u0446\u0430 20-\u043b\u0435\u0442\u0438\u044f \u041e\u043a\u0442\u044f\u0431\u0440\u044f", "building": "apartments", "building:levels": "4"}}, {"type": "way", "id": 62437197, "nodes": [779604330, 779604318, 3096875819, 3096875818, 3096869877, 3096869876, 3096869875, 3096869874, 779604305, 779604336, 779604333, 779604327, 779604320, 779604315, 779604311, 779604308, 779604330], "tags": {"addr:city": "\u0412\u043e\u0440\u043e\u043d\u0435\u0436", "addr:housenumber": "86", "addr:postcode": "394006", "addr:street": "\u0443\u043b\u0438\u0446\u0430 20-\u043b\u0435\u0442\u0438\u044f \u041e\u043a\u0442\u044f\u0431\u0440\u044f", "building": "apartments", "building:levels": "4"}}, {"type": "way", "id": 62438888, "nodes": [779616849, 779616857, 3828004561, 3828004563, 779616856, 779616853, 3828004562, 779616852, 779616859, 779616849], "tags": {"addr:city": "\u0412\u043e\u0440\u043e\u043d\u0435\u0436", "addr:housenumber": "40", "addr:postcode": "394006", "addr:street": "\u0443\u043b\u0438\u0446\u0430 \u0421\u0442\u0430\u043d\u043a\u0435\u0432\u0438\u0447\u0430", "building": "apartments", "building:levels": "4"}}, {"type": "way", "id": 62439107, "nodes": [779621883, 779621881, 779621877, 779621879, 779621883], "tags": {"addr:city": "\u0412\u043e\u0440\u043e\u043d\u0435\u0436", "addr:housenumber": "38", "addr:postcode": "394006", "addr:street": "\u0443\u043b\u0438\u0446\u0430 \u0421\u0442\u0430\u043d\u043a\u0435\u0432\u0438\u0447\u0430", "building": "apartments", "building:levels": "4"}}, {"type": "way", "id": 62768142, "nodes": [781748359, 4139506095, 781748360, 781766558, 781748363, 781755704, 781748369, 1013224464, 781748359], "tags": {"addr:city": "\u0412\u043e\u0440\u043e\u043d\u0435\u0436", "addr:housenumber": "105/2", "addr:postcode": "394006", "addr:street": "\u0443\u043b\u0438\u0446\u0430 20-\u043b\u0435\u0442\u0438\u044f \u041e\u043a\u0442\u044f\u0431\u0440\u044f", "building": "apartments", "building:levels": "5", "source:position": "bing"}}, {"type": "way", "id": 62770825, "nodes": [781755697, 781755700, 781755702, 781755704, 781748369, 781755706, 781755697], "tags": {"addr:city": "\u0412\u043e\u0440\u043e\u043d\u0435\u0436", "addr:housenumber": "105/3", "addr:postcode": "394006", "addr:street": "\u0443\u043b\u0438\u0446\u0430 20-\u043b\u0435\u0442\u0438\u044f \u041e\u043a\u0442\u044f\u0431\u0440\u044f", "building": "apartments", "building:levels": "5", "source:position": "bing"}}, {"type": "way", "id": 68604187, "nodes": [824795914, 824795911, 5153679737, 824795918, 824795916, 824795909, 824795917, 824795912, 824795910, 5153679736, 824795907, 824795913, 824795914], "tags": {"addr:city": "\u0412\u043e\u0440\u043e\u043d\u0435\u0436", "addr:housenumber": "1", "addr:postcode": "394006", "addr:street": "\u0443\u043b\u0438\u0446\u0430 \u041c\u043e\u0438\u0441\u0435\u0435\u0432\u0430", "building": "apartments", "building:levels": "5"}}, {"type": "way", "id": 68732453, "nodes": [826105777, 826105769, 826105781, 826105756, 826105759, 826105779, 826105772, 826105765, 826105777], "tags": {"addr:city": "\u0412\u043e\u0440\u043e\u043d\u0435\u0436", "addr:housenumber": "136\u0410", "addr:postcode": "394006", "addr:street": "\u0443\u043b\u0438\u0446\u0430 \u0427\u0435\u043b\u044e\u0441\u043a\u0438\u043d\u0446\u0435\u0432", "building": "apartments", "building:levels": "5", "source": "knowledge"}}, {"type": "way", "id": 68732454, "nodes": [826105763, 826105757, 826105775, 826105765, 826105777, 826105763], "tags": {"addr:city": "\u0412\u043e\u0440\u043e\u043d\u0435\u0436", "addr:housenumber": "136", "addr:postcode": "394006", "addr:street": "\u0443\u043b\u0438\u0446\u0430 \u0427\u0435\u043b\u044e\u0441\u043a\u0438\u043d\u0446\u0435\u0432", "building": "apartments", "building:levels": "5", "fire_operator": "RU-VOR-1-2", "fire_rank": "1bis"}}, {"type": "way", "id": 68732544, "nodes": [826107759, 1988051822, 1988051820, 1988051826, 1988051824, 1988051819, 1988051817, 1988051825, 1988051823, 1988051815, 1988051813, 1988051821, 826107753, 1988051839, 1988051836, 1988051859, 1988051860, 1988051864, 1988051863, 1988051883, 1988051886, 1988051890, 1988051888, 1988051897, 1988051898, 1988051902, 1988051901, 1988051906, 1988051919, 826107749, 1988051921, 1988051926, 1988051928, 1988051924, 826107763, 826107754, 826107757, 1988051904, 1988051903, 1988051899, 1988051900, 1988051896, 1988051895, 1988051892, 1988051894, 1988051881, 1988051879, 1988051865, 1988051866, 1988051862, 1988051861, 826107765, 1988051841, 1988051850, 1988051852, 1988051843, 1988051846, 1988051854, 1988051856, 1988051848, 826107761, 1988051858, 1988051857, 826107755, 826107751, 1988051827, 826107759], "tags": {"addr:city": "\u0412\u043e\u0440\u043e\u043d\u0435\u0436", "addr:housenumber": "15", "addr:postcode": "394006", "addr:street": "\u041a\u0440\u0430\u0441\u043d\u043e\u0437\u043d\u0430\u043c\u0451\u043d\u043d\u0430\u044f \u0443\u043b\u0438\u0446\u0430", "building": "apartments", "building:levels": "9"}}, {"type": "way", "id": 87122429, "nodes": [781748359, 1013224464, 1806100855, 781748375, 781748377, 781748356, 781748358, 824423082, 1806100856, 781748359], "tags": {"addr:city": "\u0412\u043e\u0440\u043e\u043d\u0435\u0436", "addr:housenumber": "105/1", "addr:postcode": "394006", "addr:street": "\u0443\u043b\u0438\u0446\u0430 20-\u043b\u0435\u0442\u0438\u044f \u041e\u043a\u0442\u044f\u0431\u0440\u044f", "building": "apartments", "building:levels": "5", "source:position": "bing"}}, {"type": "way", "id": 124171250, "nodes": [1382796062, 1382796058, 1382796045, 3656468741, 3656468742, 1382796046, 1382796044, 1382796037, 1382796043, 1382796041, 1382796047, 1382796056, 1382796060, 1382796063, 1382796062], "tags": {"addr:city": "\u0412\u043e\u0440\u043e\u043d\u0435\u0436", "addr:housenumber": "28", "addr:postcode": "394006", "addr:street": "\u0443\u043b\u0438\u0446\u0430 \u041a\u0438\u0440\u043e\u0432\u0430", "building": "apartments", "building:levels": "5", "fire_operator": "RU-VOR-1-2", "fire_rank": "1bis", "karta01.ru:name": "\u041d\u0430\u043b\u043e\u0433\u043e\u0432\u0430\u044f \u0438\u043d\u0441\u043f\u0435\u043a\u0446\u0438\u044f \u041b\u0435\u043d\u0438\u043d\u0441\u043a\u043e\u0433\u043e \u0440\u0430\u0439\u043e\u043d\u0430"}}, {"type": "way", "id": 173748789, "nodes": [1845106396, 1845106386, 1845106383, 1845106388, 1845106384, 1845106390, 1845106392, 1845106394, 1845106398, 1845106412, 1845106414, 1845106411, 1845106413, 1845106410, 1845106409, 1845106408, 1845106396], "tags": {"addr:city": "\u0412\u043e\u0440\u043e\u043d\u0435\u0436", "addr:housenumber": "88\u0415", "addr:postcode": "394006", "addr:street": "\u0443\u043b\u0438\u0446\u0430 20-\u043b\u0435\u0442\u0438\u044f \u041e\u043a\u0442\u044f\u0431\u0440\u044f", "building": "apartments", "building:levels": "17", "fire_operator": "RU-VOR-1-2", "fire_rank": "1bis", "karta01.ru:name": "\u0414\u043e\u043c \u043f\u043e\u0432\u044b\u0448\u0435\u043d\u043d\u043e\u0439 \u044d\u0442\u0430\u0436\u043d\u043e\u0441\u0442\u0438"}}, {"type": "way", "id": 306670753, "nodes": [3116421906, 3116421907, 2974330508, 3116421908, 3116421909, 2974330509, 3116421906], "tags": {"addr:city": "\u0412\u043e\u0440\u043e\u043d\u0435\u0436", "addr:housenumber": "17", "addr:postcode": "394006", "addr:street": "\u041a\u0440\u0430\u0441\u043d\u043e\u0430\u0440\u043c\u0435\u0439\u0441\u043a\u0430\u044f \u0443\u043b\u0438\u0446\u0430", "building": "apartments"}}]}