{"version": 0.6, "generator": "Overpass API 0.7.62.1 084b4234", "osm3s": {"timestamp_osm_base": "2024-05-02T20:45:50Z", "copyright": "The data included in this document is from www.openstreetmap.org. The data is made available under ODbL."}, "elements": [{"type": "node", "id": 9405019486, "lat": 54.9774185, "lon": 73.3981116}, {"type": "node", "id": 9405019487, "lat": 54.9774107, "lon": 73.3979778}, {"type": "node", "id": 9405019488, "lat": 54.9775284, "lon": 73.3980923}, {"type": "node", "id": 9405019489, "lat": 54.9775207, "lon": 73.3979585}, {"type": "way", "id": 1019718865, "nodes": [9405019488, 9405019486, 9405019487, 9405019489, 9405019488], "tags": {"building": "retail", "building:levels": "1", "roof:shape": "saltbox"}}]}