{"version": 0.6, "generator": "Overpass API 0.7.62.1 084b4234", "osm3s": {"timestamp_osm_base": "2024-05-03T14:16:56Z", "copyright": "The data included in this document is from www.openstreetmap.org. The data is made available under ODbL."}, "elements": [{"type": "node", "id": 4857440223, "lat": 44.0357767, "lon": 43.0644402, "tags": {"amenity": "bank", "name": "\u0414\u0435\u043d\u044c\u0433\u0438 \u0432 \u0440\u0443\u043a\u0438", "name:ru": "\u0414\u0435\u043d\u044c\u0433\u0438 \u0432 \u0440\u0443\u043a\u0438"}}]}