{"version": 0.6, "generator": "Overpass API 0.7.62.1 084b4234", "osm3s": {"timestamp_osm_base": "2024-05-03T02:32:41Z", "copyright": "The data included in this document is from www.openstreetmap.org. The data is made available under ODbL."}, "elements": [{"type": "node", "id": 1082313838, "lat": 56.8243354, "lon": 60.50567, "tags": {"amenity": "cafe", "brand": "\u0428\u043e\u043a\u043e\u043b\u0430\u0434\u043d\u0438\u0446\u0430", "brand:en": "Chocolate", "brand:wikidata": "Q30891188", "brand:wikipedia": "ru:\u0428\u043e\u043a\u043e\u043b\u0430\u0434\u043d\u0438\u0446\u0430 (\u0441\u0435\u0442\u044c \u043a\u043e\u0444\u0435\u0435\u043d)", "cuisine": "coffee_shop", "name": "\u0428\u043e\u043a\u043e\u043b\u0430\u0434\u043d\u0438\u0446\u0430", "name:en": "Shokoladnitsa", "operator": "\u0428\u043e\u043a\u043e\u043b\u0430\u0434\u043d\u0438\u0446\u0430", "smoking": "yes", "takeaway": "yes", "website": "https://shoko.ru/"}}, {"type": "node", "id": 1416608826, "lat": 56.8243379, "lon": 60.5048189, "tags": {"amenity": "cafe", "brand": "Cinnabon", "brand:wikidata": "Q1092539", "brand:wikipedia": "en:Cinnabon", "contact:email": "104932@megagroup.com.ru", "contact:phone": "+7 343 2879745", "contact:website": "http://cinnabonrussia.com/", "cuisine": "cake", "name": "Cinnabon", "opening_hours": "Mo-Su 10:00-22:00", "operator": "Cinnabon", "takeaway": "yes"}}, {"type": "node", "id": 2309623920, "lat": 56.8235642, "lon": 60.5044932, "tags": {"amenity": "cafe", "contact:phone": "+7 343 3565566;+7 343 3793355", "contact:website": "https://www.paulbakery.ru/", "cuisine": "french", "name": "\u041f\u043e\u043b\u044c \u0411\u0435\u0439\u043a\u0435\u0440\u0438", "opening_hours": "Mo-Su 10:00-22:00", "shop": "bakery"}}, {"type": "node", "id": 8938870710, "lat": 56.8233476, "lon": 60.5054908, "tags": {"amenity": "cafe", "brand": "\u0421\u0442\u0430\u0440\u0431\u0430\u043a\u0441", "brand:en": "Starbucks", "brand:wikidata": "Q37158", "brand:wikipedia": "en:Starbucks", "contact:email": "sbux_rus@alshaya.com", "contact:phone": "+7 499 2704040;+7 800 2227560", "contact:website": "https://www.starbucks.ru/", "cuisine": "coffee_shop", "diet:vegan": "no", "diet:vegetarian": "yes", "name": "\u0421\u0442\u0430\u0440\u0431\u0430\u043a\u0441", "name:en": "Starbucks", "opening_hours": "Mo-Su 10:00-22:00", "takeaway": "yes"}}]}