{"version": 0.6, "generator": "Overpass API 0.7.62.1 084b4234", "osm3s": {"timestamp_osm_base": "2024-05-03T17:43:29Z", "copyright": "The data included in this document is from www.openstreetmap.org. The data is made available under ODbL."}, "elements": [{"type": "node", "id": 4630115771, "lat": 56.8523433, "lon": 35.9084858, "tags": {"amenity": "restaurant", "capacity": "50", "level": "0", "name": "\u0424\u0440\u0435\u0448 \u0411\u0443\u0444\u0435\u0442", "outdoor_seating": "no", "takeaway": "no", "website": "https://freshbufet.ru/"}}, {"type": "node", "id": 6781377450, "lat": 56.8534149, "lon": 35.9078455, "tags": {"amenity": "restaurant", "bar": "yes", "cuisine": "pizza;italian;\u0438\u0442\u0430\u043b\u044c\u044f\u043d\u0441\u043a\u0430\u044f;\u0421\u0443\u0448\u0438", "internet_access": "yes", "name": "Penates (Fabula Group)", "phone": "+7 4822 631031"}}]}