{"version": 0.6, "generator": "Overpass API 0.7.62.1 084b4234", "osm3s": {"timestamp_osm_base": "2024-05-03T16:56:56Z", "copyright": "The data included in this document is from www.openstreetmap.org. The data is made available under ODbL."}, "elements": [{"type": "node", "id": 1218294655, "lat": 56.1505815, "lon": 40.3730731}, {"type": "node", "id": 1218294665, "lat": 56.1506778, "lon": 40.3731658}, {"type": "node", "id": 1218294678, "lat": 56.1504419, "lon": 40.3735402}, {"type": "node", "id": 1218294686, "lat": 56.1505382, "lon": 40.373633}, {"type": "way", "id": 105808687, "nodes": [1218294655, 1218294665, 1218294686, 1218294678, 1218294655], "tags": {"addr:city": "\u0412\u043b\u0430\u0434\u0438\u043c\u0438\u0440", "addr:country": "RU", "addr:housenumber": "94", "addr:street": "\u0443\u043b\u0438\u0446\u0430 \u0413\u043e\u0440\u044c\u043a\u043e\u0433\u043e", "building": "commercial", "building:levels": "4", "name": "\u0422\u0414 \"\u0412\u0438\u043a\u043e\u043b\"", "roof:shape": "hipped"}}]}