{"version": 0.6, "generator": "Overpass API 0.7.62.1 084b4234", "osm3s": {"timestamp_osm_base": "2024-05-03T09:06:00Z", "copyright": "The data included in this document is from www.openstreetmap.org. The data is made available under ODbL."}, "elements": [{"type": "node", "id": 3261247022, "lat": 56.0603041, "lon": 92.9144128}, {"type": "node", "id": 3261247041, "lat": 56.0600759, "lon": 92.9128473}, {"type": "node", "id": 3261247042, "lat": 56.0605089, "lon": 92.9121396}, {"type": "node", "id": 3261247045, "lat": 56.0608267, "lon": 92.9130013}, {"type": "node", "id": 3261247046, "lat": 56.0609861, "lon": 92.9133041}, {"type": "node", "id": 3261247051, "lat": 56.0608949, "lon": 92.9128921}, {"type": "node", "id": 3261247056, "lat": 56.0601237, "lon": 92.9129393}, {"type": "node", "id": 3261247058, "lat": 56.0598215, "lon": 92.9134837}, {"type": "way", "id": 319670116, "nodes": [3261247051, 3261247042, 3261247041, 3261247056, 3261247058, 3261247022, 3261247046, 3261247045, 3261247051], "tags": {"amenity": "kindergarten", "barrier": "fence", "name": "\u0414\u0435\u0442\u0441\u043a\u0438\u0439 \u0441\u0430\u0434 \u2116\u00a074"}}]}