{"version": 0.6, "generator": "Overpass API 0.7.62.1 084b4234", "osm3s": {"timestamp_osm_base": "2024-05-02T21:03:00Z", "copyright": "The data included in this document is from www.openstreetmap.org. The data is made available under ODbL."}, "elements": [{"type": "node", "id": 4721894688, "lat": 54.3804847, "lon": 48.5948925}, {"type": "node", "id": 4721895289, "lat": 54.3804206, "lon": 48.5949776}, {"type": "node", "id": 4721895290, "lat": 54.3804645, "lon": 48.5950748}, {"type": "node", "id": 4721895291, "lat": 54.380348, "lon": 48.5952297}, {"type": "node", "id": 4721895292, "lat": 54.3805444, "lon": 48.5956654}, {"type": "node", "id": 4721895293, "lat": 54.3804517, "lon": 48.5957887}, {"type": "node", "id": 4721895294, "lat": 54.3805981, "lon": 48.5961133}, {"type": "node", "id": 4721895295, "lat": 54.3808714, "lon": 48.5957501}, {"type": "node", "id": 4721895296, "lat": 54.3808073, "lon": 48.5958352}, {"type": "node", "id": 7153388675, "lat": 54.3804847, "lon": 48.5948925}, {"type": "node", "id": 7153388676, "lat": 54.3804206, "lon": 48.5949776}, {"type": "node", "id": 7153388677, "lat": 54.3804645, "lon": 48.5950748}, {"type": "node", "id": 7153388678, "lat": 54.3808714, "lon": 48.5957501}, {"type": "way", "id": 479024472, "nodes": [4721894688, 4721895289, 4721895290, 4721895291, 4721895292, 4721895293, 4721895294, 4721895296, 4721895295, 4721894688], "tags": {"addr:housenumber": "27\u0410", "addr:street": "\u043f\u0440\u043e\u0441\u043f\u0435\u043a\u0442 \u041b\u0435\u043d\u0438\u043d\u0441\u043a\u043e\u0433\u043e \u041a\u043e\u043c\u0441\u043e\u043c\u043e\u043b\u0430", "building": "hotel", "building:levels": "9", "contact:facebook": "https://www.facebook.com/ibis", "contact:facebook_1": "https://www.facebook.com/groups/971792306205681/", "contact:google_plus": "https://plus.google.com/+ibis", "contact:twitter": "https://twitter.com/ibis_ulsk", "contact:vk": "https://vk.com/club96249604", "contact:youtube": "https://www.youtube.com/ibis", "name": "\u0410\u0432\u0438\u0430\u0442\u043e\u0440", "operator": "Accor", "roof:shape": "flat", "start_date": "2018-04-26", "tourism": "hotel"}}, {"type": "way", "id": 479024477, "nodes": [7153388675, 7153388676, 7153388677, 4721895296, 7153388678, 7153388675], "tags": {"building": "hotel", "building:levels": "1", "roof:shape": "flat"}}, {"type": "way", "id": 479024479, "nodes": [4721895290, 4721895291, 4721895292, 4721895293, 4721895294, 4721895296, 4721895290], "tags": {"building": "hotel", "building:levels": "9", "roof:shape": "flat"}}]}