{"version": 0.6, "generator": "Overpass API 0.7.62.1 084b4234", "osm3s": {"timestamp_osm_base": "2024-05-03T14:33:30Z", "copyright": "The data included in this document is from www.openstreetmap.org. The data is made available under ODbL."}, "elements": [{"type": "node", "id": 8724338774, "lat": 55.7829279, "lon": 49.2356989}, {"type": "node", "id": 8724338775, "lat": 55.7830124, "lon": 49.2356426}, {"type": "node", "id": 8724338776, "lat": 55.78302, "lon": 49.2357887}, {"type": "node", "id": 8724338777, "lat": 55.7830848, "lon": 49.2361374}, {"type": "node", "id": 8724338778, "lat": 55.7828344, "lon": 49.2365196}, {"type": "node", "id": 8724338779, "lat": 55.782839, "lon": 49.2366135}, {"type": "node", "id": 8724338780, "lat": 55.7827243, "lon": 49.236694}, {"type": "node", "id": 8724338781, "lat": 55.7824943, "lon": 49.2361012}, {"type": "node", "id": 8724338782, "lat": 55.7825577, "lon": 49.2360033}, {"type": "way", "id": 942123147, "nodes": [8724338782, 8724338781, 8724338780, 8724338779, 8724338778, 8724338777, 8724338776, 8724338775, 8724338774, 8724338782], "tags": {"amenity": "fuel", "fuel:diesel": "yes", "fuel:octane_92": "yes", "fuel:octane_95": "yes", "fuel:octane_98": "yes", "internet_access": "wlan", "internet_access:fee": "no", "name": "\u0418\u0440\u0431\u0438\u0441", "name:en": "Irbis", "name:ru": "\u0418\u0440\u0431\u0438\u0441", "payment:cash": "yes", "payment:contactless": "yes", "payment:mastercard": "yes", "payment:visa": "yes", "payment:visa_debit": "yes", "payment:visa_electron": "yes", "toilets": "yes"}}]}