{"version": 0.6, "generator": "Overpass API 0.7.62.1 084b4234", "osm3s": {"timestamp_osm_base": "2024-05-03T23:14:26Z", "copyright": "The data included in this document is from www.openstreetmap.org. The data is made available under ODbL."}, "elements": [{"type": "node", "id": 654886052, "lat": 59.9277902, "lon": 30.3706855}, {"type": "node", "id": 654887839, "lat": 59.9278505, "lon": 30.3711164}, {"type": "node", "id": 654887990, "lat": 59.927938, "lon": 30.3708749}, {"type": "node", "id": 654887991, "lat": 59.92776, "lon": 30.3709848}, {"type": "node", "id": 654888051, "lat": 59.9276604, "lon": 30.3712575}, {"type": "node", "id": 654888052, "lat": 59.9276107, "lon": 30.3711852}, {"type": "node", "id": 5578613708, "lat": 59.9278671, "lon": 30.3707765}, {"type": "node", "id": 5578613709, "lat": 59.9277815, "lon": 30.3710155}, {"type": "node", "id": 10178654852, "lat": 59.927882, "lon": 30.3707972, "tags": {"entrance": "staircase"}}, {"type": "way", "id": 51326868, "nodes": [654887990, 654887839, 5578613709, 654887991, 654888051, 654888052, 654886052, 5578613708, 10178654852, 654887990], "tags": {"addr:city": "\u0421\u0430\u043d\u043a\u0442-\u041f\u0435\u0442\u0435\u0440\u0431\u0443\u0440\u0433", "addr:country": "RU", "addr:housenumber": "8", "addr:postcode": "191024", "addr:street": "\u041f\u043e\u043b\u0442\u0430\u0432\u0441\u043a\u0430\u044f \u0443\u043b\u0438\u0446\u0430", "building": "residential", "building:levels": "4"}}]}