{"version": 0.6, "generator": "Overpass API 0.7.62.1 084b4234", "osm3s": {"timestamp_osm_base": "2024-05-03T17:03:01Z", "copyright": "The data included in this document is from www.openstreetmap.org. The data is made available under ODbL."}, "elements": [{"type": "node", "id": 1850148956, "lat": 55.1110684, "lon": 61.6112532}, {"type": "node", "id": 1850148961, "lat": 55.1111754, "lon": 61.6102395}, {"type": "node", "id": 1850148977, "lat": 55.1120552, "lon": 61.6115883}, {"type": "node", "id": 1850148981, "lat": 55.1121456, "lon": 61.6105408}, {"type": "node", "id": 3186333907, "lat": 55.1135368, "lon": 61.6119213}, {"type": "node", "id": 3186333908, "lat": 55.1126185, "lon": 61.611815}, {"type": "node", "id": 7774022210, "lat": 55.1136302, "lon": 61.6101205}, {"type": "node", "id": 7774022211, "lat": 55.1126614, "lon": 61.6099757}, {"type": "node", "id": 7774022212, "lat": 55.1125301, "lon": 61.6102713}, {"type": "node", "id": 7774022213, "lat": 55.1137881, "lon": 61.6104457}, {"type": "node", "id": 7775147879, "lat": 55.1126159, "lon": 61.6118838}, {"type": "node", "id": 7775147880, "lat": 55.1135342, "lon": 61.6119901}, {"type": "node", "id": 7776131750, "lat": 55.1133457, "lon": 61.6122398}, {"type": "node", "id": 7776131751, "lat": 55.1128885, "lon": 61.6121821}, {"type": "node", "id": 7776131752, "lat": 55.1128853, "lon": 61.6122615}, {"type": "node", "id": 7776131753, "lat": 55.1133424, "lon": 61.6123192}, {"type": "way", "id": 174326232, "nodes": [1850148977, 1850148956, 1850148961, 1850148981, 1850148977], "tags": {"amenity": "parking", "barrier": "fence", "fee": "yes", "parking": "surface"}}, {"type": "way", "id": 312744871, "nodes": [7775147880, 3186333907, 3186333908, 7775147879, 7775147880], "tags": {"amenity": "parking", "parking": "street_side"}}, {"type": "way", "id": 832711554, "nodes": [7774022213, 7774022212, 7774022211, 7774022210, 7774022213], "tags": {"amenity": "parking", "parking": "surface"}}, {"type": "way", "id": 832985474, "nodes": [7776131753, 7776131752, 7776131751, 7776131750, 7776131753], "tags": {"access": "yes", "amenity": "parking", "fee": "no", "parking": "surface"}}]}