{"version": 0.6, "generator": "Overpass API 0.7.62.1 084b4234", "osm3s": {"timestamp_osm_base": "2024-05-03T17:48:30Z", "copyright": "The data included in this document is from www.openstreetmap.org. The data is made available under ODbL."}, "elements": [{"type": "node", "id": 9447062972, "lat": 46.9309256, "lon": 142.7473569, "tags": {"amenity": "clinic", "contact:phone": "+7 423 2242124;+7 424 2736968;+7 800 5555569", "contact:website": "http://unilab.su/", "healthcare": "clinic", "name": "\u042e\u043d\u0438\u043b\u0430\u0431", "opening_hours": "Mo-Fr 07:30-17:00;Sa 08:00-14:00"}}]}